memory_mcp_server/__init__.py
memory_mcp_server/exceptions.py
memory_mcp_server/interfaces.py
memory_mcp_server/knowledge_graph_manager.py
memory_mcp_server/validation.py
memory_mcp_server/backends/__init__.py
memory_mcp_server/backends/base.py
memory_mcp_server/backends/jsonl.py
mseep_memory_mcp_server-0.2.2.dist-info/licenses/LICENSE
mseep_memory_mcp_server-0.2.2.dist-info/METADATA
mseep_memory_mcp_server-0.2.2.dist-info/WHEEL
mseep_memory_mcp_server-0.2.2.dist-info/top_level.txt
mseep_memory_mcp_server-0.2.2.dist-info/RECORD
