Metadata-Version: 2.4
Name: mseep-memory-mcp-server
Version: 0.2.2
Summary: MCP server for managing Claude's memory and knowledge graph
Home-page: 
Author: mseep
Author-email: mseep <support@skydeck.ai>
Maintainer-email: mseep <support@skydeck.ai>
Requires-Python: >=3.6
License-File: LICENSE
Requires-Dist: aiofiles
Requires-Dist: loguru>=0.7.3
Requires-Dist: mcp[cli]>=1.2.0
Requires-Dist: memory-mcp-server
Requires-Dist: ruff>=0.9.4
Requires-Dist: thefuzz[speedup]>=0.20.0
Provides-Extra: test
Requires-Dist: pytest; extra == "test"
Requires-Dist: pytest-asyncio; extra == "test"
Requires-Dist: pytest-cov; extra == "test"
Dynamic: author
Dynamic: license-file
Dynamic: requires-python
